ai/backend/common/VERSION
ai/backend/common/__init__.py
ai/backend/common/api_handlers.py
ai/backend/common/arch.py
ai/backend/common/argparse.py
ai/backend/common/artifact_storage.py
ai/backend/common/asyncio.py
ai/backend/common/cgroup.py
ai/backend/common/cli.py
ai/backend/common/config.py
ai/backend/common/container_registry.py
ai/backend/common/distributed.py
ai/backend/common/docker.py
ai/backend/common/enum_extension.py
ai/backend/common/etcd.py
ai/backend/common/exception.py
ai/backend/common/files.py
ai/backend/common/identity.py
ai/backend/common/json.py
ai/backend/common/lock.py
ai/backend/common/logging.py
ai/backend/common/logging_utils.py
ai/backend/common/msgpack.py
ai/backend/common/netns.py
ai/backend/common/networking.py
ai/backend/common/py.typed
ai/backend/common/redis_client.py
ai/backend/common/redis_helper.py
ai/backend/common/sd_notify.py
ai/backend/common/service_ports.py
ai/backend/common/testutils.py
ai/backend/common/typed_validators.py
ai/backend/common/types.py
ai/backend/common/utils.py
ai/backend/common/validators.py
ai/backend/common/auth/__init__.py
ai/backend/common/auth/utils.py
ai/backend/common/bgtask/__init__.py
ai/backend/common/bgtask/bgtask.py
ai/backend/common/bgtask/exception.py
ai/backend/common/bgtask/reporter.py
ai/backend/common/bgtask/task_result.py
ai/backend/common/bgtask/types.py
ai/backend/common/bgtask/hooks/__init__.py
ai/backend/common/bgtask/hooks/base.py
ai/backend/common/bgtask/hooks/composite_hook.py
ai/backend/common/bgtask/hooks/event_hook.py
ai/backend/common/bgtask/hooks/metric_hook.py
ai/backend/common/bgtask/hooks/valkey_hook.py
ai/backend/common/bgtask/task/__init__.py
ai/backend/common/bgtask/task/base.py
ai/backend/common/bgtask/task/registry.py
ai/backend/common/clients/__init__.py
ai/backend/common/clients/http_client/__init__.py
ai/backend/common/clients/http_client/client_pool.py
ai/backend/common/clients/valkey_client/__init__.py
ai/backend/common/clients/valkey_client/client.py
backend_ai_common-26.1.0.dist-info/METADATA
backend_ai_common-26.1.0.dist-info/WHEEL
backend_ai_common-26.1.0.dist-info/namespace_packages.txt
backend_ai_common-26.1.0.dist-info/top_level.txt
backend_ai_common-26.1.0.dist-info/RECORD
